deepforest/IoU.py
deepforest/__init__.py
deepforest/_version.py
deepforest/callbacks.py
deepforest/dataset.py
deepforest/evaluate.py
deepforest/main.py
deepforest/model.py
deepforest/predict.py
deepforest/preprocess.py
deepforest/utilities.py
deepforest/visualize.py
deepforest/data/2019_YELL_2_528000_4978000_image_crop2.png
deepforest/data/2019_YELL_2_528000_4978000_image_crop2.xml
deepforest/data/2019_YELL_2_541000_4977000_image_crop.png
deepforest/data/2019_YELL_2_541000_4977000_image_crop.xml
deepforest/data/OSBS_029.csv
deepforest/data/OSBS_029.png
deepforest/data/OSBS_029.tif
deepforest/data/OSBS_029.xml
deepforest/data/SOAP_031.png
deepforest/data/SOAP_061.png
deepforest/data/SOAP_061.xml
deepforest/data/__init__.py
deepforest/data/classes.csv
deepforest/data/deepforest_config.yml
deepforest/data/example.csv
deepforest/data/testfile_deepforest.csv
deepforest/data/testfile_multi.csv
tests/__init__.py
tests/conftest.py
tests/profile_dataset.py
tests/profile_evaluate.py
tests/profile_predict_file.py
tests/test_IoU.py
tests/test_callbacks.py
tests/test_data.py
tests/test_dataset.py
tests/test_environment.py
tests/test_evaluate.py
tests/test_main.py
tests/test_model.py
tests/test_preprocess.py
tests/test_utilities.py
tests/test_visualize.py
deepforest_pytorch-0.2.3.dist-info/AUTHORS.rst
deepforest_pytorch-0.2.3.dist-info/LICENSE
deepforest_pytorch-0.2.3.dist-info/METADATA
deepforest_pytorch-0.2.3.dist-info/WHEEL
deepforest_pytorch-0.2.3.dist-info/top_level.txt
deepforest_pytorch-0.2.3.dist-info/RECORD
