Metadata-Version: 2.1
Name: deepforest-pytorch
Version: 0.2.3
Summary: Tree crown prediction using deep learning retinanets
Home-page: https://github.com/Weecology/DeepForest-pytorch
Author: Ben Weinstein
License: MIT
Platform: UNKNOWN
Requires-Python: >3.5
Requires-Dist: torch
Requires-Dist: torchvision
Requires-Dist: matplotlib
Requires-Dist: Pillow (>6.2.0)
Requires-Dist: pandas
Requires-Dist: progressbar2
Requires-Dist: six
Requires-Dist: scipy (>1.5)
Requires-Dist: slidingwindow
Requires-Dist: geopandas
Requires-Dist: rasterio
Requires-Dist: rtree
Requires-Dist: pytorch-lightning
Requires-Dist: tqdm
Requires-Dist: xmltodict
Requires-Dist: numpy
Requires-Dist: imagecodecs
Requires-Dist: albumentations
